tests/__init__.py
tests/context.py
tests/backend/__init__.py
tests/backend/test_config.py
tests/backend/test_json.py
tests/backend/test_metadata.py
tests/backend/test_sqlite.py
tests/cli/__init__.py
tests/cli/test_add.py
tests/cli/test_config.py
tests/cli/test_edit.py
tests/cli/test_init.py
tests/cli/test_note.py
tests/cli/test_open.py
tests/cli/test_tag.py
tests/parse/__init__.py
tests/parse/test_arxiv.py
tests/parse/test_citekey.py
tests/parse/test_classification.py
tests/parse/test_doi.py
tests/parse/test_isbn.py
tests/parse/test_normalization.py
tests/parse/test_pdf.py
tests/parse/test_yaml.py
zoia/__init__.py
zoia/_version.py
zoia/cli/__init__.py
zoia/cli/add.py
zoia/cli/cli.py
zoia/cli/config.py
zoia/cli/edit.py
zoia/cli/init.py
zoia/cli/note.py
zoia/cli/open.py
zoia/cli/tag.py
zoia/parse/__init__.py
zoia/parse/arxiv.py
zoia/parse/citekey.py
zoia/parse/classification.py
zoia/parse/doi.py
zoia/parse/isbn.py
zoia/parse/normalization.py
zoia/parse/pdf.py
zoia/parse/yaml.py
zoia-0.2.1.dist-info/LICENSE
zoia-0.2.1.dist-info/METADATA
zoia-0.2.1.dist-info/WHEEL
zoia-0.2.1.dist-info/entry_points.txt
zoia-0.2.1.dist-info/top_level.txt
zoia-0.2.1.dist-info/RECORD
