Metadata-Version: 2.1
Name: zoia
Version: 0.2.1
Summary: Command line tool to manage references.
Home-page: https://github.com/joe-antognini/zoia
Author: Joseph Antognini
Author-email: joe.antognini@gmail.com
License: MIT
Platform: UNKNOWN
Classifier: Development Status :: 3 - Alpha
Classifier: Intended Audience :: Science/Research
Classifier: Natural Language :: English
Classifier: Programming Language :: Python :: 3
Classifier: License :: OSI Approved :: MIT License
Classifier: Operating System :: POSIX
Requires-Python: >=3.8
Requires-Dist: bibtexparser (>=1.2.0)
Requires-Dist: click (>=7.1.2)
Requires-Dist: halo (>=0.0.30)
Requires-Dist: isbnlib (>=3.10.3)
Requires-Dist: pdfminer.six (>=20200726)
Requires-Dist: pyyaml (>=5.3.1)
Requires-Dist: requests (>=2.24.0)
Requires-Dist: sqlalchemy (>=1.3.19)
